semicon/__init__.py
semicon/_static_version.py
semicon/_version.py
semicon/misc.py
semicon/model_cache.json
semicon/models.py
semicon/parameters.py
semicon/peierls.py
semicon/symbols.py
semicon/databank/bank_lawaetz.yml
semicon/databank/bank_winkler.yml
semicon/kp_models/__init__.py
semicon/kp_models/explicit_foreman.py
semicon/kp_models/explicit_zeeman.py
semicon/kp_models/symbols.py
semicon/tests/__init__.py
semicon/tests/test_misc.py
semicon/tests/test_models.py
semicon/tests/test_parameters.py
semicon/tests/test_zincblende.py
semicon-0.2.0.dist-info/LICENSE
semicon-0.2.0.dist-info/METADATA
semicon-0.2.0.dist-info/WHEEL
semicon-0.2.0.dist-info/top_level.txt
semicon-0.2.0.dist-info/RECORD
