Metadata-Version: 2.1
Name: semicon
Version: 0.2.0
Summary: Package for simulating quantum mechanical k·p Hamiltonians
Home-page: https://gitlab.kwant-project.org/semicon/semicon
Author: R.J. Skolasinski
Author-email: r.j.skolasinski@gmail.com
License: BSD
Platform: Unix
Platform: Linux
Classifier: Development Status :: 3 - Alpha
Classifier: Intended Audience :: Science/Research
Classifier: Intended Audience :: Developers
Classifier: Programming Language :: Python :: 3 :: Only
Classifier: Topic :: Software Development
Classifier: Topic :: Scientific/Engineering
Classifier: Operating System :: POSIX
Classifier: Operating System :: Unix
Requires-Dist: pyyaml
Requires-Dist: scipy (>=0.17)
Requires-Dist: kwant (>=1.3)
Requires-Dist: sympy (>=1.1.1)
Requires-Dist: pandas (>=0.19.2)
